CHANGELOG
LICENSE
MANIFEST.in
README.rst
gzip_reader.py
setup.py
gzip_reader.egg-info/PKG-INFO
gzip_reader.egg-info/SOURCES.txt
gzip_reader.egg-info/dependency_links.txt
gzip_reader.egg-info/pbr.json
gzip_reader.egg-info/top_level.txt