Metadata-Version: 1.1
Name: gzip-reader
Version: 0.1
Summary: Decompress gzipped streams on the fly
Home-page: http://github.com/Suor/gzip-reader
Author: Alexander Schepanovski
Author-email: suor.web@gmail.com
License: BSD
Platform: UNKNOWN
Classifier: Development Status :: 4 - Beta
Classifier: License :: OSI Approved :: BSD License
Classifier: Operating System :: OS Independent
Classifier: Programming Language :: Python
Classifier: Programming Language :: Python :: 2
Classifier: Programming Language :: Python :: 2.7
Classifier: Programming Language :: Python :: Implementation :: CPython
Classifier: Topic :: Software Development :: Libraries :: Python Modules
Classifier: Intended Audience :: Developers
